rift/__init__.py
rift/bin/compare.py
rift/bin/job_scheduler_resolver.py
rift/bin/kill_proc_subproc.sh
rift/conf/__init__.py
rift/conf/environment.py
rift/conf/global_settings.py
rift/conf/mock_settings.py
rift/conf/reader.py
rift/core/__init__.py
rift/core/main.py
rift/core/mock.py
rift/core/scheduler.py
rift/core/source.py
rift/factories/__init__.py
rift/factories/test_case_factory.py
rift/management/__init__.py
rift/management/cli.py
rift/model/__init__.py
rift/model/exec_section.py
rift/model/git_section.py
rift/model/test_case.py
rift/paths/__init__.py
rift/paths/execution_paths_mixin.py
rift/paths/global_paths_mixin.py
rift/paths/path_manager.py
rift/paths/test_case_paths_mixin.py
rift/paths/utils.py
rift/shell/load_modules.sh
rift/shell/start.sh
rift/shell/util/datetime.sh
rift/shell/util/deprecated.sh
rift/shell/util/log.sh
rift/shell/util/submit.sh
rift/shell/utils.sh
rift/utils/__init__.py
rift/utils/log.py
rift/utils/module_loading.py
pit_rift-0.1.5.dist-info/LICENSE
pit_rift-0.1.5.dist-info/METADATA
pit_rift-0.1.5.dist-info/WHEEL
pit_rift-0.1.5.dist-info/entry_points.txt
pit_rift-0.1.5.dist-info/RECORD
