Metadata-Version: 2.1
Name: pit-rift
Version: 0.1.5
Summary: Parametrized Integration Testing framework Tool
Keywords: test,intragration testing,CI/CD,devops,test suite
Author: Antonio Mariani
Author-email: antonio.mariani@cmcc.it
Requires-Python: >=3.10,<4.0
Classifier: Programming Language :: Python :: 3
Classifier: Programming Language :: Python :: 3.10
Classifier: Programming Language :: Python :: 3.11
Classifier: Programming Language :: Python :: 3.12
Requires-Dist: psutil (>=6.0.0,<7.0.0)
Requires-Dist: pydantic (>=2.8.2,<3.0.0)
Requires-Dist: pytest (>=8.3.2,<9.0.0)
Requires-Dist: pytest-mock (>=3.14.0,<4.0.0)
Requires-Dist: pyyaml (>=6.0.1,<7.0.0)
